handle_missing_values.py
handle_missing_values-0.0.1.dist-info/LICENSE.txt
handle_missing_values-0.0.1.dist-info/METADATA
handle_missing_values-0.0.1.dist-info/WHEEL
handle_missing_values-0.0.1.dist-info/top_level.txt
handle_missing_values-0.0.1.dist-info/RECORD
