Metadata-Version: 2.1
Name: handle-missing-values
Version: 0.0.1
Summary: Handle missing values in a csv file
Home-page: https://github.com/pypa/sampleproject
Author: Keshav Bansal
Author-email: keshavbansal509@gmail.com
License: UNKNOWN
Platform: UNKNOWN
Classifier: Programming Language :: Python :: 3
Classifier: License :: OSI Approved :: MIT License
Classifier: Operating System :: OS Independent
Requires-Python: >=3.6
